azure/__init__.py
azure/cli/__init__.py
azure/cli/command_modules/__init__.py
azure/cli/command_modules/iot/__init__.py
azure/cli/command_modules/iot/_client_factory.py
azure/cli/command_modules/iot/_constants.py
azure/cli/command_modules/iot/_help.py
azure/cli/command_modules/iot/_params.py
azure/cli/command_modules/iot/_utils.py
azure/cli/command_modules/iot/_validators.py
azure/cli/command_modules/iot/commands.py
azure/cli/command_modules/iot/custom.py
azure/cli/command_modules/iot/sas_token_auth.py
azure/cli/command_modules/iot/shared.py
azure/cli/command_modules/iot/digitaltwinrepositoryprovisioningservice/__init__.py
azure/cli/command_modules/iot/digitaltwinrepositoryprovisioningservice/digital_twin_repository_provisioning_service.py
azure/cli/command_modules/iot/digitaltwinrepositoryprovisioningservice/version.py
azure/cli/command_modules/iot/digitaltwinrepositoryprovisioningservice/models/__init__.py
azure/cli/command_modules/iot/digitaltwinrepositoryprovisioningservice/models/key_metadata.py
azure/cli/command_modules/iot/digitaltwinrepositoryprovisioningservice/models/repository_key_request.py
azure/cli/command_modules/iot/digitaltwinrepositoryprovisioningservice/models/repository_key_request_properties.py
azure/cli/command_modules/iot/digitaltwinrepositoryprovisioningservice/models/repository_metadata.py
azure/cli/command_modules/iot/digitaltwinrepositoryprovisioningservice/models/repository_metadata_properties.py
azure/cli/command_modules/iot/digitaltwinrepositoryprovisioningservice/models/repository_provision_response_base.py
azure/cli/command_modules/iot/digitaltwinrepositoryprovisioningservice/models/repository_upsert_request.py
azure/cli/command_modules/iot/digitaltwinrepositoryprovisioningservice/models/repository_upsert_request_properties.py
azure/cli/command_modules/iot/mgmt_iot_hub_device/__init__.py
azure/cli/command_modules/iot/mgmt_iot_hub_device/lib/__init__.py
azure/cli/command_modules/iot/mgmt_iot_hub_device/lib/credentials.py
azure_cli_iot-0.3.11.dist-info/METADATA
azure_cli_iot-0.3.11.dist-info/WHEEL
azure_cli_iot-0.3.11.dist-info/top_level.txt
azure_cli_iot-0.3.11.dist-info/RECORD
